<annotation>
	<folder>in</folder>
	<filename>9e9f36145ca070adacb04706ef969dedf2e688d7.png</filename>
	<path>in/9e9f36145ca070adacb04706ef969dedf2e688d7.png</path>
	<source>
		<database>Unknown</database>
	</source>
	<size>
		<width>300</width>
		<height>300</height>
		<depth>3</depth>
	</size>
	<segmented>0</segmented>
	<object>
		<name>egg</name>
		<pose>Unspecified</pose>
		<truncated>0</truncated>
		<difficult>0</difficult>
		<bndbox>
			<xmin>3</xmin>
			<ymin>90</ymin>
			<xmax>85</xmax>
			<ymax>164</ymax>
		</bndbox>
	</object>
	<object>
		<name>egg</name>
		<pose>Unspecified</pose>
		<truncated>0</truncated>
		<difficult>0</difficult>
		<bndbox>
			<xmin>64</xmin>
			<ymin>36</ymin>
			<xmax>129</xmax>
			<ymax>120</ymax>
		</bndbox>
	</object>
	<object>
		<name>egg</name>
		<pose>Unspecified</pose>
		<truncated>0</truncated>
		<difficult>0</difficult>
		<bndbox>
			<xmin>123</xmin>
			<ymin>62</ymin>
			<xmax>200</xmax>
			<ymax>138</ymax>
		</bndbox>
	</object>
	<object>
		<name>egg</name>
		<pose>Unspecified</pose>
		<truncated>0</truncated>
		<difficult>0</difficult>
		<bndbox>
			<xmin>185</xmin>
			<ymin>106</ymin>
			<xmax>273</xmax>
			<ymax>170</ymax>
		</bndbox>
	</object>
	<object>
		<name>egg</name>
		<pose>Unspecified</pose>
		<truncated>0</truncated>
		<difficult>0</difficult>
		<bndbox>
			<xmin>165</xmin>
			<ymin>176</ymin>
			<xmax>250</xmax>
			<ymax>239</ymax>
		</bndbox>
	</object>
</annotation>